odoo/addons/l10n_it_fatturapa_out_stamp/README.rst
odoo/addons/l10n_it_fatturapa_out_stamp/__init__.py
odoo/addons/l10n_it_fatturapa_out_stamp/__manifest__.py
odoo/addons/l10n_it_fatturapa_out_stamp/i18n/it.po
odoo/addons/l10n_it_fatturapa_out_stamp/i18n/l10n_it_fatturapa_out_stamp.pot
odoo/addons/l10n_it_fatturapa_out_stamp/readme/CONTRIBUTORS.md
odoo/addons/l10n_it_fatturapa_out_stamp/readme/DESCRIPTION.md
odoo/addons/l10n_it_fatturapa_out_stamp/static/description/icon.png
odoo/addons/l10n_it_fatturapa_out_stamp/static/description/index.html
odoo/addons/l10n_it_fatturapa_out_stamp/views/account_invoice_it_dati_bollo.xml
odoo_addon_l10n_it_fatturapa_out_stamp-16.0.1.0.1.1.dist-info/METADATA
odoo_addon_l10n_it_fatturapa_out_stamp-16.0.1.0.1.1.dist-info/WHEEL
odoo_addon_l10n_it_fatturapa_out_stamp-16.0.1.0.1.1.dist-info/top_level.txt
odoo_addon_l10n_it_fatturapa_out_stamp-16.0.1.0.1.1.dist-info/RECORD
