Metadata-Version: 2.1
Name: odoo-addon-l10n_it_fatturapa_out_stamp
Version: 16.0.1.0.1.1
Requires-Python: >=3.10
Requires-Dist: odoo-addon-l10n_it_account_stamp>=16.0dev,<16.1dev
Requires-Dist: odoo-addon-l10n_it_fatturapa_out>=16.0dev,<16.1dev
Requires-Dist: odoo>=16.0a,<16.1dev
Summary: Modulo ponte tra emissione fatture elettroniche e imposta di bollo
Home-page: https://github.com/OCA/l10n-italy
License: AGPL-3
Author: Agile Business Group, Odoo Community Association (OCA)
Author-email: support@odoo-community.org
Classifier: Programming Language :: Python
Classifier: Framework :: Odoo
Classifier: Framework :: Odoo :: 16.0
Classifier: License :: OSI Approved :: GNU Affero General Public License v3
Classifier: Development Status :: 4 - Beta
